Meine/__init__.py
Meine/app.py
Meine/exceptions.py
Meine/logger_config.py
Meine/main.py
Meine/themes.py
Meine/ui_handler.py
Meine/Actions/Myrequest.py
Meine/Actions/__init__.py
Meine/Actions/compress.py
Meine/Actions/file.py
Meine/Actions/other.py
Meine/Actions/system.py
Meine/resources/customs.json
Meine/resources/history.json
Meine/resources/quotes.json
Meine/resources/settings.json
Meine/screens/__init__.py
Meine/screens/help.py
Meine/screens/home.py
Meine/screens/me.py
Meine/screens/settings.py
Meine/screens/textarea.py
Meine/tcss/app.tcss
Meine/tcss/help.tcss
Meine/tcss/me.tcss
Meine/tcss/setting.tcss
Meine/utils/__init__.py
Meine/utils/file_manager.py
Meine/widgets/__init__.py
Meine/widgets/containers.py
Meine/widgets/directory_tree.py
Meine/widgets/input.py
meinere-1.0.3.dist-info/licenses/LICENSE
meinere-1.0.3.dist-info/METADATA
meinere-1.0.3.dist-info/WHEEL
meinere-1.0.3.dist-info/entry_points.txt
meinere-1.0.3.dist-info/top_level.txt
meinere-1.0.3.dist-info/RECORD
