Metadata-Version: 2.4
Name: Meinere
Version: 1.0.3
Summary: ⚡MeineRe - A regex-powered, asynchronous CLI file manager and system utility built with Textual. It combines intuitive command parsing with rich terminal UI, allowing you to navigate directories, manage files, and fetch system info—fast.
Author-email: balaji j <j.balaji2468@gmail.com>
License: MIT License
Classifier: Programming Language :: Python :: 3
Classifier: License :: OSI Approved :: MIT License
Classifier: Operating System :: OS Independent
Requires-Python: >=3.11
License-File: LICENSE
Requires-Dist: aiofiles==24.1.0
Requires-Dist: appdirs==1.4.4
Requires-Dist: Brotli==1.1.0
Requires-Dist: build==1.2.2.post1
Requires-Dist: inflate64==1.0.1
Requires-Dist: linkify-it-py==2.0.3
Requires-Dist: markdown-it-py==3.0.0
Requires-Dist: mdit-py-plugins==0.4.2
Requires-Dist: mdurl==0.1.2
Requires-Dist: multivolumefile==0.2.3
Requires-Dist: packaging==25.0
Requires-Dist: platformdirs==4.3.7
Requires-Dist: psutil==7.0.0
Requires-Dist: py7zr==0.22.0
Requires-Dist: pybcj==1.0.3
Requires-Dist: pycryptodomex==3.22.0
Requires-Dist: Pygments==2.19.1
Requires-Dist: pyppmd==1.1.1
Requires-Dist: pyproject_hooks==1.2.0
Requires-Dist: pyzstd==0.16.2
Requires-Dist: rich==14.0.0
Requires-Dist: texttable==1.7.0
Requires-Dist: textual==3.1.0
Requires-Dist: tree-sitter==0.24.0
Requires-Dist: tree-sitter-bash==0.23.3
Requires-Dist: tree-sitter-css==0.23.2
Requires-Dist: tree-sitter-go==0.23.4
Requires-Dist: tree-sitter-html==0.23.2
Requires-Dist: tree-sitter-java==0.23.5
Requires-Dist: tree-sitter-javascript==0.23.1
Requires-Dist: tree-sitter-json==0.24.8
Requires-Dist: tree-sitter-markdown==0.3.2
Requires-Dist: tree-sitter-python==0.23.6
Requires-Dist: tree-sitter-regex==0.24.3
Requires-Dist: tree-sitter-rust==0.24.0
Requires-Dist: tree-sitter-sql==0.3.7
Requires-Dist: tree-sitter-toml==0.7.0
Requires-Dist: tree-sitter-xml==0.7.0
Requires-Dist: tree-sitter-yaml==0.7.0
Requires-Dist: typing_extensions==4.13.2
Requires-Dist: uc-micro-py==1.0.3
Requires-Dist: xdialog==1.2.0.1
Requires-Dist: click==8.1.8
Dynamic: license-file
